azcati/__init__.py
azcati/azcati_cloud.py
azcati-0.0.9.dist-info/LICENSE
azcati-0.0.9.dist-info/METADATA
azcati-0.0.9.dist-info/WHEEL
azcati-0.0.9.dist-info/top_level.txt
azcati-0.0.9.dist-info/RECORD
